README.rst
setup.py
maggit/__init__.py
maggit/config.py
maggit/const.py
maggit/git_objects.py
maggit/refs.py
maggit/repo.py
maggit/sha.py
maggit.egg-info/PKG-INFO
maggit.egg-info/SOURCES.txt
maggit.egg-info/dependency_links.txt
maggit.egg-info/top_level.txt
maggit/db/__init__.py
maggit/db/db.py
maggit/db/ref_handler.py
maggit/db/repo.py
maggit/io/__init__.py
maggit/io/config.py
maggit/io/index.py
maggit/io/loose.py
maggit/io/pack.py
maggit/io/packedref.py