Metadata-Version: 1.1
Name: maggit
Version: 0.1
Summary: A python implemetation of git
Home-page: UNKNOWN
Author: Matthieu Gautier
Author-email: dev@mgautier.fr
License: AGPLv3+ with "Lesser" clause
Keywords: git
Platform: UNKNOWN
Classifier: Operating System :: OS Independent
Classifier: Programming Language :: Python :: 3.4
Classifier: License :: OSI Approved :: GNU Affero General Public License v3 or later (AGPLv3+)
Classifier: Development Status :: 3 - Alpha
Classifier: Intended Audience :: Developers
Classifier: Topic :: Software Development :: Libraries :: Python Modules
